rockset_v2/__init__.py
rockset_v2/api/__init__.py
rockset_v2/api/aliases_api.py
rockset_v2/api/api_keys_api.py
rockset_v2/api/collections_api.py
rockset_v2/api/custom_roles_api.py
rockset_v2/api/documents_api.py
rockset_v2/api/integrations_api.py
rockset_v2/api/organizations_api.py
rockset_v2/api/queries_api.py
rockset_v2/api/query_lambdas_api.py
rockset_v2/api/shared_lambdas_api.py
rockset_v2/api/users_api.py
rockset_v2/api/views_api.py
rockset_v2/api/virtual_instances_api.py
rockset_v2/api/workspaces_api.py
rockset_v2/api_client.py
rockset_v2/apis/__init__.py
rockset_v2/configuration.py
rockset_v2/document.py
rockset_v2/exceptions.py
rockset_v2/model/__init__.py
rockset_v2/model/add_documents_request.py
rockset_v2/model/add_documents_response.py
rockset_v2/model/alias.py
rockset_v2/model/api_key.py
rockset_v2/model/async_query_options.py
rockset_v2/model/auto_scaling_policy.py
rockset_v2/model/aws_access_key.py
rockset_v2/model/aws_role.py
rockset_v2/model/azure_blob_storage_collection_creation_request.py
rockset_v2/model/azure_blob_storage_integration.py
rockset_v2/model/azure_blob_storage_integration_creation_request.py
rockset_v2/model/azure_blob_storage_source_wrapper.py
rockset_v2/model/azure_event_hubs_collection_creation_request.py
rockset_v2/model/azure_event_hubs_integration.py
rockset_v2/model/azure_event_hubs_integration_creation_request.py
rockset_v2/model/azure_event_hubs_source_wrapper.py
rockset_v2/model/azure_service_bus_collection_creation_request.py
rockset_v2/model/azure_service_bus_integration.py
rockset_v2/model/azure_service_bus_source_wrapper.py
rockset_v2/model/bulk_stats.py
rockset_v2/model/cancel_query_response.py
rockset_v2/model/cluster.py
rockset_v2/model/collection.py
rockset_v2/model/collection_mount.py
rockset_v2/model/collection_mount_response.py
rockset_v2/model/collection_mount_stats.py
rockset_v2/model/collection_stats.py
rockset_v2/model/create_alias_request.py
rockset_v2/model/create_alias_response.py
rockset_v2-2.0.2.dist-info/METADATA
rockset_v2-2.0.2.dist-info/WHEEL
rockset_v2-2.0.2.dist-info/RECORD
